[
  {
    "mes": "Junio",
    "dia": 8,
    "dow": "Lun",
    "cat": "matrimonios",
    "titulo": "Matrimonios ÉL VIVE, KIDS y Juntas de Comunidad e Iniciación"
  },
  {
    "mes": "Junio",
    "dia": 10,
    "dow": "Mié",
    "cat": "consejo",
    "titulo": "Junta de Consejo"
  },
  {
    "mes": "Junio",
    "dia": 17,
    "dow": "Mié",
    "cat": "consejo",
    "titulo": "Junta de Consejo"
  },
  {
    "mes": "Junio",
    "dia": 30,
    "dow": "Mar",
    "cat": "apostolado",
    "titulo": "Apostolado mensual",
    "desc": "Lugar y hora por definir"
  },
  {
    "mes": "Julio",
    "dia": 1,
    "dow": "Mié",
    "cat": "consejo",
    "titulo": "Junta de Consejo"
  },
  {
    "mes": "Julio",
    "dia": 5,
    "dow": "Dom",
    "cat": "misa",
    "titulo": "Misa mensual",
    "hora": "5:00 p.m.",
    "desc": "Domingo"
  },
  {
    "mes": "Julio",
    "dia": 6,
    "dow": "Lun",
    "cat": "matrimonios",
    "titulo": "Matrimonios ÉL VIVE, KIDS y Juntas de Comunidad e Iniciación"
  },
  {
    "mes": "Julio",
    "dia": 15,
    "dow": "Mié",
    "cat": "consejo",
    "titulo": "Junta de Consejo"
  },
  {
    "mes": "Julio",
    "dia": "24 – 26",
    "dow": "Vie a Dom",
    "cat": "especial",
    "titulo": "Retiro #121 de Monterrey",
    "desc": "Nos unimos todos en oración",
    "rango": true
  },
  {
    "mes": "Julio",
    "dia": 29,
    "dow": "Mié",
    "cat": "consejo",
    "titulo": "Junta de Consejo"
  },
  {
    "mes": "Julio",
    "dia": "31 – 2",
    "dow": "Vie a Dom",
    "cat": "especial",
    "titulo": "Retiro #122 de Monterrey",
    "desc": "Nos unimos todos en oración",
    "rango": true
  },
  {
    "mes": "Julio",
    "dia": "",
    "dow": "",
    "cat": "apostolado",
    "titulo": "Apostolado mensual",
    "desc": "Lugar y fecha exacta por definir"
  },
  {
    "mes": "Agosto",
    "dia": "3 – 16",
    "dow": "Lun a Dom",
    "cat": "especial",
    "titulo": "Vacaciones",
    "desc": "Del lunes 3 al domingo 16 de agosto.",
    "rango": true
  },
  {
    "mes": "Agosto",
    "dia": 11,
    "dow": "Mar",
    "cat": "misa",
    "titulo": "Misa por el 30.º Aniversario de la Comunidad ÉL VIVE"
  },
  {
    "mes": "Agosto",
    "dia": 19,
    "dow": "Mié",
    "cat": "consejo",
    "titulo": "Junta de Consejo"
  },
  {
    "mes": "Agosto",
    "dia": 29,
    "dow": "Sáb",
    "cat": "economica",
    "titulo": "Actividad económica chica"
  },
  {
    "mes": "Agosto",
    "dia": 29,
    "dow": "Sáb",
    "cat": "misa",
    "titulo": "Misa mensual",
    "hora": "5:00 p.m.",
    "desc": "Sabado"
  },
  {
    "mes": "Agosto",
    "dia": 31,
    "dow": "Lun",
    "cat": "matrimonios",
    "titulo": "Matrimonios ÉL VIVE, KIDS y Juntas de Comunidad e Iniciación"
  },
  {
    "mes": "Agosto",
    "dia": "",
    "dow": "",
    "cat": "apostolado",
    "titulo": "Apostolado mensual",
    "desc": "Lugar y fecha exacta por definir"
  },
  {
    "mes": "Septiembre",
    "dia": "4 – 6",
    "dow": "Vie a Dom",
    "cat": "especial",
    "titulo": "Retiro #3 de Chihuahua",
    "desc": "Nos unimos todos en oración",
    "rango": true
  },
  {
    "mes": "Septiembre",
    "dia": 5,
    "dow": "Sáb",
    "cat": "misa",
    "titulo": "Misa de Niños",
    "hora": "5:00 p.m.",
    "desc": "Sabado"
  },
  {
    "mes": "Septiembre",
    "dia": 9,
    "dow": "Mié",
    "cat": "consejo",
    "titulo": "Junta de Consejo"
  },
  {
    "mes": "Septiembre",
    "dia": 15,
    "dow": "Mar",
    "cat": "economica",
    "titulo": "Kermés de la Parroquia La Resurrección"
  },
  {
    "mes": "Septiembre",
    "dia": 23,
    "dow": "Mié",
    "cat": "consejo",
    "titulo": "Junta de Consejo"
  },
  {
    "mes": "Septiembre",
    "dia": 26,
    "dow": "Sáb",
    "cat": "misa",
    "titulo": "Misa mensual",
    "hora": "5:00 p.m.",
    "desc": "Sabado"
  },
  {
    "mes": "Septiembre",
    "dia": 28,
    "dow": "Lun",
    "cat": "matrimonios",
    "titulo": "Matrimonios ÉL VIVE, KIDS y Juntas de Comunidad e Iniciación"
  },
  {
    "mes": "Septiembre",
    "dia": "",
    "dow": "",
    "cat": "apostolado",
    "titulo": "Apostolado mensual",
    "desc": "Lugar y fecha exacta por definir"
  },
  {
    "mes": "Octubre",
    "dia": 7,
    "dow": "Mié",
    "cat": "consejo",
    "titulo": "Junta de Consejo"
  },
  {
    "mes": "Octubre",
    "dia": 10,
    "dow": "Sáb",
    "cat": "especial",
    "titulo": "Primera limpieza de rancho con Comunidad de Iniciación 1",
    "desc": "Incluye un momento de convivencia, oración y encuentro en el rancho."
  },
  {
    "mes": "Octubre",
    "dia": 21,
    "dow": "Mié",
    "cat": "consejo",
    "titulo": "Junta de Consejo"
  },
  {
    "mes": "Octubre",
    "dia": 24,
    "dow": "Sáb",
    "cat": "economica",
    "titulo": "Actividad económica grande (Conferencias)"
  },
  {
    "mes": "Octubre",
    "dia": 24,
    "dow": "Sáb",
    "cat": "misa",
    "titulo": "Misa mensual",
    "hora": "5:00 p.m.",
    "desc": "Sabado"
  },
  {
    "mes": "Octubre",
    "dia": 26,
    "dow": "Lun",
    "cat": "matrimonios",
    "titulo": "Matrimonios ÉL VIVE, KIDS y Juntas de Comunidad e Iniciación"
  },
  {
    "mes": "Octubre",
    "dia": 27,
    "dow": "Mar",
    "cat": "especial",
    "titulo": "Inicio de invitaciones para el Retiro de Compromiso 1"
  },
  {
    "mes": "Octubre",
    "dia": "",
    "dow": "",
    "cat": "apostolado",
    "titulo": "Apostolado mensual",
    "desc": "Lugar y fecha exacta por definir"
  },
  {
    "mes": "Noviembre",
    "dia": 2,
    "dow": "Lun",
    "cat": "economica",
    "titulo": "Inicio de la Mega Rifa"
  },
  {
    "mes": "Noviembre",
    "dia": 4,
    "dow": "Mié",
    "cat": "consejo",
    "titulo": "Junta de Consejo"
  },
  {
    "mes": "Noviembre",
    "dia": 14,
    "dow": "Sáb",
    "cat": "misa",
    "titulo": "Misa mensual y convivencia con KIDS",
    "hora": "5:00 p.m.",
    "desc": "(O apostolado con KIDS, por definir.)"
  },
  {
    "mes": "Noviembre",
    "dia": 18,
    "dow": "Mié",
    "cat": "consejo",
    "titulo": "Junta de Consejo"
  },
  {
    "mes": "Noviembre",
    "dia": 23,
    "dow": "Lun",
    "cat": "matrimonios",
    "titulo": "Matrimonios ÉL VIVE, KIDS y Juntas de Comunidad e Iniciación"
  },
  {
    "mes": "Noviembre",
    "dia": 28,
    "dow": "Sáb",
    "cat": "especial",
    "titulo": "Limpieza de rancho"
  },
  {
    "mes": "Noviembre",
    "dia": "",
    "dow": "",
    "cat": "apostolado",
    "titulo": "Apostolado mensual",
    "desc": "Lugar y fecha exacta por definir"
  },
  {
    "mes": "Diciembre",
    "dia": 2,
    "dow": "Mié",
    "cat": "consejo",
    "titulo": "Junta de Consejo"
  },
  {
    "mes": "Diciembre",
    "dia": 8,
    "dow": "Mar",
    "cat": "economica",
    "titulo": "Mega Rifa"
  },
  {
    "mes": "Diciembre",
    "dia": 11,
    "dow": "Vie",
    "cat": "especial",
    "titulo": "Peregrinación"
  },
  {
    "mes": "Diciembre",
    "dia": 12,
    "dow": "Sáb",
    "cat": "especial",
    "titulo": "Día de la Virgen, misa y Posada KIDS"
  },
  {
    "mes": "Diciembre",
    "dia": 14,
    "dow": "Lun",
    "cat": "especial",
    "titulo": "Posada durante la junta",
    "desc": "Última junta del mes de diciembre."
  },
  {
    "mes": "Diciembre",
    "dia": 16,
    "dow": "Mié",
    "cat": "consejo",
    "titulo": "Junta de Consejo"
  },
  {
    "mes": "Diciembre",
    "dia": 17,
    "dow": "Jue",
    "cat": "especial",
    "titulo": "Última Hora Santa del año"
  },
  {
    "mes": "Diciembre",
    "dia": "",
    "dow": "",
    "cat": "apostolado",
    "titulo": "Apostolado mensual",
    "desc": "Lugar y fecha exacta por definir"
  }
]